{
  "cell": "ED|Performer",
  "copingSub": "PE-2",
  "family": "ED",
  "locale": "zh-CN",
  "originSub": "ED-2",
  "style": "Performer",
  "tag": "ED-2_PE-2",
  "variants": [
    {
      "fields": {
        "crime": [
          "她只有一次收起笑话说了真话。隔着桌子说自己撑不住了，对面的人递过来一块巧克力，接着低头看杂志。",
          "家里人从小就是这么打发她的：她一开口，就给她买点什么，没有人听她说话。",
          "下手挑在洗澡的时段。她把洗手池堵上塞子灌满水，按住那个人的头，自己一直低声笑着。笑着的嗓子喊不出救命，人就这么淹死了。",
          "这段时间里，会客厅里她的手机正放着一场冒充直播的段子，其实是上礼拜录好的四十分钟。",
          "当天傍晚，在淋浴房里排队等着的几个人记得，自己无缘无故笑到发疼。而会客厅里有一个心情正差的观众，从头到尾一声没笑。",
          "录下来的笑声只是声音，带不动任何人。既然有观众全程没笑，会客厅里放的就是录音。"
        ],
        "epitaph": "递到她手里的东西，从来都包着一层纸。",
        "epithet": "用零钱打发的小丑",
        "execution": [
          "处刑台正中摆着一把椅子。她被按在椅子上坐下，囚犯们围着处刑台站成一圈。",
          "推进来的机器每隔几秒吐出一只系着缎带的小盒，往她脚边、膝上、肩头堆，比她伸手去挡还快。",
          "盒子全是空的。",
          "直到那堆东西不再动了，机器才停下来。"
        ],
        "magic": "她一笑，听见的人就都跟着笑，直到她停下来为止。"
      },
      "variant": 1
    }
  ]
}
